LICENSE
README.md
pyproject.toml
setup.cfg
tgui/__init__.py
tgui.egg-info/PKG-INFO
tgui.egg-info/SOURCES.txt
tgui.egg-info/dependency_links.txt
tgui.egg-info/requires.txt
tgui.egg-info/top_level.txt
tgui/src/constructor/factories/checks_factory.py
tgui/src/constructor/factories/fields_factory.py
tgui/src/constructor/factories/validators_factory.py
tgui/src/constructor/models/choice.py
tgui/src/constructor/models/choice_button.py
tgui/src/constructor/models/form.py
tgui/src/constructor/models/multiple_choice.py
tgui/src/constructor/models/validated_item.py
tgui/src/constructor/models/validator_types.py
tgui/src/constructor/models/yes_no.py
tgui/src/constructor/utils/prove_pieces.py
tgui/src/domain/destination.py
tgui/src/domain/emoji.py
tgui/src/domain/piece.py
tgui/src/domain/validators.py
tgui/src/logging/exception_handler.py
tgui/src/logging/logger_wrapper.py
tgui/src/logging/tg_logger.py
tgui/src/logging/tg_logger_stream.py
tgui/src/logging/tg_universal_logger.py
tgui/src/managers/callback_query_manager.py
tgui/src/managers/dont_press_egg.py
tgui/src/managers/media_grouper.py
tgui/src/managers/texter.py
tgui/src/managers/tg_state_binder.py
tgui/src/mixin/executable.py
tgui/src/mixin/tg_message_translate_mixin.py
tgui/src/states/branch.py
tgui/src/states/form.py
tgui/src/states/input_field.py
tgui/src/states/list.py
tgui/src/states/multiple_choice.py
tgui/src/states/paging.py
tgui/src/states/ref_list.py
tgui/src/states/tg_state.py
tgui/src/utils/calculate_tg_state.py
tgui/src/utils/send_message.py
tgui/src/utils/utils.py