Metadata-Version: 2.1
Name: tgui
Version: 1.0.15
Summary: Wrapper of telebot
Author-email: Chersky <lega4e@lega4e.ru>
Maintainer-email: Chersky <lega4e@lega4e.ru>
License: MIT License
Project-URL: Repository, https://github.com/lega4e/tgui.git
Keywords: lega4e,telegram,telebot
Requires-Python: >=3.9
License-File: LICENSE
Requires-Dist: lega4e_library>=0.0.7
Requires-Dist: pyTelegramBotAPI>=4.20.0
Requires-Dist: aiohttp>=3.10.9
Requires-Dist: pytils>=0.4.1
